shin-0.2.2.dist-info/METADATA
shin-0.2.2.dist-info/WHEEL
shin-0.2.2.dist-info/licenses/LICENSE
shin.libs/libgcc_s-98a1ef30.so.1
shin/__init__.py
shin/py.typed
shin/shin.cpython-310-x86_64-linux-gnu.so
shin/shin.pyi
shin-0.2.2.dist-info/RECORD
