Metadata-Version: 2.4
Name: shin
Version: 0.2.2
Classifier: Programming Language :: Rust
Classifier: Programming Language :: Python :: Implementation :: CPython
Classifier: Programming Language :: Python :: Implementation :: PyPy
Classifier: Programming Language :: Python :: 3.13
Classifier: License :: OSI Approved :: MIT License
Classifier: Operating System :: OS Independent
License-File: LICENSE
Summary: Python implementation of Shin's method for calculating implied probabilities from bookmaker odds
Author-email: Maurice Berk <maurice@mauriceberk.com>
Requires-Python: >=3.9
Project-URL: Repository, https://github.com/mberk/shin
